Verilog/adder.v
module adder(a0,a1,a2,a3,b0,b1,b2,b3,cin,cout,s0,s1,s2,s3);

input a0,a1,a2,a3,b0,b1,b2,b3,cin;
output cout,s0,s1,s2,s3;
wire p0,p1,p2,p3,g0,g1,g2,g3,c1,c2,c3,c1_i1,c2_i1,c2_i2,c3_i1,c3_i2,c3_i3,c4_i1,c4_i2,c4_i3,c4_i4;

// P and G block 
xor G1(p0,a0,b0);
xor G2(p1,a1,b1);
xor G3(p2,a2,b2);
xor G4(p3,a3,b3);

and G5(g0,a0,b0);
and G6(g1,a1,b1);
and G7(g2,a2,b2);
and G8(g3,a3,b3);

// CLA block 

and G9(c1_i1,p0,cin);
or G10(c1,g0,c1_i1);
//
and G11(c2_i1,p1,p0,cin);
and G12(c2_i2,p1,g0);
or G13(c2,g1,c2_i1,c2_i2);
//
and G14(c3_i1,p2,p1,p0,cin);
and G15(c3_i2,p2,p1,g0);
and G16(c3_i3,p2,g1);
or G17(c3,g2,c3_i1,c3_i2,c3_i3);
//
and G18(c4_i1,p3,p2,p1,p0,cin);
and G19(c4_i2,p3,p2,p1,g0);
and G20(c4_i3,p3,p2,g1);
and G21(c4_i4,p3,g2);
or G22(cout,g3,c4_i1,c4_i2,c4_i3,c4_i4);

// SUM block

xor X5(s0,cin,p0);
xor X6(s1,c1,p1);
xor X7(s2,c2,p2);
xor X8(s3,c3,p3);

endmodule

Verilog/testbench.v
module test();

reg a0,a1,a2,a3,b0,b1,b2,b3,cin;
wire s0,s1,s2,s3,cout;
integer k;

adder dut(a0,a1,a2,a3,b0,b1,b2,b3,cin,cout,s0,s1,s2,s3);

initial begin
cin=0;
$dumpfile("adder.vcd");
$dumpvars(0,test);

for(k=0;k<257;k=k+1)
begin
{a3,b3,a2,b2,a1,b1,a0,b0}=k;#5;
end
end

always @ (*)
begin
#1
$display("A = %b%b%b%b  B = %b%b%b%b  Cin = %b \nS = %b%b%b%b Cout = %b" ,a3,a2,a1,a0,b3,b2,b1,b0,cin,s3,s2,s1,s0,cout);
end

endmodule

Verilog/adder.vcd
$date
	Mon Dec  6 23:35:45 2021
$end
$version
	Icarus Verilog
$end
$timescale
	1s
$end
$scope module test $end
$var wire 1 ! s3 $end
$var wire 1 " s2 $end
$var wire 1 # s1 $end
$var wire 1 $ s0 $end
$var wire 1 % cout $end
$var reg 1 & a0 $end
$var reg 1 ' a1 $end
$var reg 1 ( a2 $end
$var reg 1 ) a3 $end
$var reg 1 * b0 $end
$var reg 1 + b1 $end
$var reg 1 , b2 $end
$var reg 1 - b3 $end
$var reg 1 . cin $end
$var integer 32 / k [31:0] $end
$scope module dut $end
$var wire 1 & a0 $end
$var wire 1 ' a1 $end
$var wire 1 ( a2 $end
$var wire 1 ) a3 $end
$var wire 1 * b0 $end
$var wire 1 + b1 $end
$var wire 1 , b2 $end
$var wire 1 - b3 $end
$var wire 1 0 c1 $end
$var wire 1 1 c1_i1 $end
$var wire 1 2 c2 $end
$var wire 1 3 c2_i1 $end
$var wire 1 4 c2_i2 $end
$var wire 1 5 c3 $end
$var wire 1 6 c3_i1 $end
$var wire 1 7 c3_i2 $end
$var wire 1 8 c3_i3 $end
$var wire 1 9 c4_i1 $end
$var wire 1 : c4_i2 $end
$var wire 1 ; c4_i3 $end
$var wire 1 < c4_i4 $end
$var wire 1 . cin $end
$var wire 1 % cout $end
$var wire 1 = g0 $end
$var wire 1 > g1 $end
$var wire 1 ? g2 $end
$var wire 1 @ g3 $end
$var wire 1 A p0 $end
$var wire 1 B p1 $end
$var wire 1 C p2 $end
$var wire 1 D p3 $end
$var wire 1 $ s0 $end
$var wire 1 # s1 $end
$var wire 1 " s2 $end
$var wire 1 ! s3 $end
$upscope $end
$upscope $end
$enddefinitions $end
#0
$dumpvars
0D
0C
0B
0A
0@
0?
0>
0=
0<
0;
0:
09
08
07
06
05
04
03
02
01
00
b0 /
0.
0-
0,
0+
0*
0)
0(
0'
0&
0%
0$
0#
0"
0!
$end
#5
1$
1A
1*
b1 /
#10
1&
0*
b10 /
#15
1#
0$
10
0A
1=
1*
b11 /
#20
00
1B
0=
1+
0&
0*
b100 /
#25
1$
1A
1*
b101 /
#30
1&
0*
b110 /
#35
1"
0#
12
0$
10
14
0A
1=
1*
b111 /
#40
0"
1#
02
00
04
0=
1'
0+
0&
0*
b1000 /
#45
1$
1A
1*
b1001 /
#50
1&
0*
b1010 /
#55
1"
0#
12
0$
10
14
0A
1=
1*
b1011 /
#60
00
04
0B
1>
0=
1+
0&
0*
b1100 /
#65
1$
1A
1*
b1101 /
#70
1&
0*
b1110 /
#75
1#
0$
10
0A
1=
1*
b1111 /
#80
0#
02
00
1C
0>
0=
1,
0'
0+
0&
0*
b10000 /
#85
1$
1A
1*
b10001 /
#90
1&
0*
b10010 /
#95
1#
0$
10
0A
1=
1*
b10011 /
#100
00
1B
0=
1+
0&
0*
b10100 /
#105
1$
1A
1*
b10101 /
#110
1&
0*
b10110 /
#115
0"
1!
0#
12
15
0$
10
14
17
0A
1=
1*
b10111 /
#120
1"
0!
1#
02
05
00
04
07
0=
1'
0+
0&
0*
b11000 /
#125
1$
1A
1*
b11001 /
#130
1&
0*
b11010 /
#135
0"
1!
0#
12
15
0$
10
14
17
0A
1=
1*
b11011 /
#140
18
00
04
07
0B
1>
0=
1+
0&
0*
b11100 /
#145
1$
1A
1*
b11101 /
#150
1&
0*
b11110 /
#155
1#
0$
10
0A
1=
1*
b11111 /
#160
0!
1"
05
0#
02
08
00
0>
0=
1(
0,
0'
0+
0&
0*
b100000 /
#165
1$
1A
1*
b100001 /
#170
1&
0*
b100010 /
#175
1#
0$
10
0A
1=
1*
b100011 /
#180
00
1B
0=
1+
0&
0*
b100100 /
#185
1$
1A
1*
b100101 /
#190
1&
0*
b100110 /
#195
0"
1!
0#
12
15
0$
10
14
17
0A
1=
1*
b100111 /
#200
1"
0!
1#
02
05
00
04
07
0=
1'
0+
0&
0*
b101000 /
#205
1$
1A
1*
b101001 /
#210
1&
0*
b101010 /
#215
0"
1!
0#
12
15
0$
10
14
17
0A
1=
1*
b101011 /
#220
18
00
04
07
0B
1>
0=
1+
0&
0*
b101100 /
#225
1$
1A
1*
b101101 /
#230
1&
0*
b101110 /
#235
1#
0$
10
0A
1=
1*
b101111 /
#240
0#
02
08
00
0C
1?
0>
0=
1,
0'
0+
0&
0*
b110000 /
#245
1$
1A
1*
b110001 /
#250
1&
0*
b110010 /
#255
1#
0$
10
0A
1=
1*
b110011 /
#260
00
1B
0=
1+
0&
0*
b110100 /
#265
1$
1A
1*
b110101 /
#270
1&
0*
b110110 /
#275
1"
0#
12
0$
10
14
0A
1=
1*
b110111 /
#280
0"
1#
02
00
04
0=
1'
0+
0&
0*
b111000 /
#285
1$
1A
1*
b111001 /
#290
1&
0*
b111010 /
#295
1"
0#
12
0$
10
14
0A
1=
1*
b111011 /
#300
00
04
0B
1>
0=
1+
0&
0*
b111100 /
#305
1$
1A
1*
b111101 /
#310
1&
0*
b111110 /
#315
1#
0$
10
0A
1=
1*
b111111 /
#320
0"
0#
05
02
00
1D
0?
0>
0=
1-
0(
0,
0'
0+
0&
0*
b1000000 /
#325
1$
1A
1*
b1000001 /
#330
1&
0*
b1000010 /
#335
1#
0$
10
0A
1=
1*
b1000011 /
#340
00
1B
0=
1+
0&
0*
b1000100 /
#345
1$
1A
1*
b1000101 /
#350
1&
0*
b1000110 /
#355
1"
0#
12
0$
10
14
0A
1=
1*
b1000111 /
#360
0"
1#
02
00
04
0=
1'
0+
0&
0*
b1001000 /
#365
1$
1A
1*
b1001001 /
#370
1&
0*
b1001010 /
#375
1"
0#
12
0$
10
14
0A
1=
1*
b1001011 /
#380
00
04
0B
1>
0=
1+
0&
0*
b1001100 /
#385
1$
1A
1*
b1001101 /
#390
1&
0*
b1001110 /
#395
1#
0$
10
0A
1=
1*
b1001111 /
#400
0#
02
00
1C
0>
0=
1,
0'
0+
0&
0*
b1010000 /
#405
1$
1A
1*
b1010001 /
#410
1&
0*
b1010010 /
#415
1#
0$
10
0A
1=
1*
b1010011 /
#420
00
1B
0=
1+
0&
0*
b1010100 /
#425
1$
1A
1*
b1010101 /
#430
1&
0*
b1010110 /
#435
0"
0!
1%
0#
12
15
0$
10
14
17
1:
0A
1=
1*
b1010111 /
#440
1"
1!
0%
1#
02
05
00
04
07
0:
0=
1'
0+
0&
0*
b1011000 /
#445
1$
1A
1*
b1011001 /
#450
1&
0*
b1011010 /
#455
0"
0!
1%
0#
12
15
0$
10
14
17
1:
0A
1=
1*
b1011011 /
#460
18
1;
00
04
07
0:
0B
1>
0=
1+
0&
0*
b1011100 /
#465
1$
1A
1*
b1011101 /
#470
1&
0*
b1011110 /
#475
1#
0$
10
0A
1=
1*
b1011111 /
#480
1!
0%
1"
05
0#
02
08
0;
00
0>
0=
1(
0,
0'
0+
0&
0*
b1100000 /
#485
1$
1A
1*
b1100001 /
#490
1&
0*
b1100010 /
#495
1#
0$
10
0A
1=
1*
b1100011 /
#500
00
1B
0=
1+
0&
0*
b1100100 /
#505
1$
1A
1*
b1100101 /
#510
1&
0*
b1100110 /
#515
0"
0!
1%
0#
12
15
0$
10
14
17
1:
0A
1=
1*
b1100111 /
#520
1"
1!
0%
1#
02
05
00
04
07
0:
0=
1'
0+
0&
0*
b1101000 /
#525
1$
1A
1*
b1101001 /
#530
1&
0*
b1101010 /
#535
0"
0!
1%
0#
12
15
0$
10
14
17
1:
0A
1=
1*
b1101011 /
#540
18
1;
00
04
07
0:
0B
1>
0=
1+
0&
0*
b1101100 /
#545
1$
1A
1*
b1101101 /
#550
1&
0*
b1101110 /
#555
1#
0$
10
0A
1=
1*
b1101111 /
#560
0#
1<
02
08
0;
00
0C
1?
0>
0=
1,
0'
0+
0&
0*
b1110000 /
#565
1$
1A
1*
b1110001 /
#570
1&
0*
b1110010 /
#575
1#
0$
10
0A
1=
1*
b1110011 /
#580
00
1B
0=
1+
0&
0*
b1110100 /
#585
1$
1A
1*
b1110101 /
#590
1&
0*
b1110110 /
#595
1"
0#
12
0$
10
14
0A
1=
1*
b1110111 /
#600
0"
1#
02
00
04
0=
1'
0+
0&
0*
b1111000 /
#605
1$
1A
1*
b1111001 /
#610
1&
0*
b1111010 /
#615
1"
0#
12
0$
10
14
0A
1=
1*
b1111011 /
#620
00
04
0B
1>
0=
1+
0&
0*
b1111100 /
#625
1$
1A
1*
b1111101 /
#630
1&
0*
b1111110 /
#635
1#
0$
10
0A
1=
1*
b1111111 /
#640
0%
1!
0"
0#
05
0<
02
00
0?
0>
0=
1)
0-
0(
0,
0'
0+
0&
0*
b10000000 /
#645
1$
1A
1*
b10000001 /
#650
1&
0*
b10000010 /
#655
1#
0$
10
0A
1=
1*
b10000011 /
#660
00
1B
0=
1+
0&
0*
b10000100 /
#665
1$
1A
1*
b10000101 /
#670
1&
0*
b10000110 /
#675
1"
0#
12
0$
10
14
0A
1=
1*
b10000111 /
#680
0"
1#
02
00
04
0=
1'
0+
0&
0*
b10001000 /
#685
1$
1A
1*
b10001001 /
#690
1&
0*
b10001010 /
#695
1"
0#
12
0$
10
14
0A
1=
1*
b10001011 /
#700
00
04
0B
1>
0=
1+
0&
0*
b10001100 /
#705
1$
1A
1*
b10001101 /
#710
1&
0*
b10001110 /
#715
1#
0$
10
0A
1=
1*
b10001111 /
#720
0#
02
00
1C
0>
0=
1,
0'
0+
0&
0*
b10010000 /
#725
1$
1A
1*
b10010001 /
#730
1&
0*
b10010010 /
#735
1#
0$
10
0A
1=
1*
b10010011 /
#740
00
1B
0=
1+
0&
0*
b10010100 /
#745
1$
1A
1*
b10010101 /
#750
1&
0*
b10010110 /
#755
0"
0!
1%
0#
12
15
0$
10
14
17
1:
0A
1=
1*
b10010111 /
#760
1"
1!
0%
1#
02
05
00
04
07
0:
0=
1'
0+
0&
0*
b10011000 /
#765
1$
1A
1*
b10011001 /
#770
1&
0*
b10011010 /
#775
0"
0!
1%
0#
12
15
0$
10
14
17
1:
0A
1=
1*
b10011011 /
#780
18
1;
00
04
07
0:
0B
1>
0=
1+
0&
0*
b10011100 /
#785
1$
1A
1*
b10011101 /
#790
1&
0*
b10011110 /
#795
1#
0$
10
0A
1=
1*
b10011111 /
#800
1!
0%
1"
05
0#
02
08
0;
00
0>
0=
1(
0,
0'
0+
0&
0*
b10100000 /
#805
1$
1A
1*
b10100001 /
#810
1&
0*
b10100010 /
#815
1#
0$
10
0A
1=
1*
b10100011 /
#820
00
1B
0=
1+
0&
0*
b10100100 /
#825
1$
1A
1*
b10100101 /
#830
1&
0*
b10100110 /
#835
0"
0!
1%
0#
12
15
0$
10
14
17
1:
0A
1=
1*
b10100111 /
#840
1"
1!
0%
1#
02
05
00
04
07
0:
0=
1'
0+
0&
0*
b10101000 /
#845
1$
1A
1*
b10101001 /
#850
1&
0*
b10101010 /
#855
0"
0!
1%
0#
12
15
0$
10
14
17
1:
0A
1=
1*
b10101011 /
#860
18
1;
00
04
07
0:
0B
1>
0=
1+
0&
0*
b10101100 /
#865
1$
1A
1*
b10101101 /
#870
1&
0*
b10101110 /
#875
1#
0$
10
0A
1=
1*
b10101111 /
#880
0#
1<
02
08
0;
00
0C
1?
0>
0=
1,
0'
0+
0&
0*
b10110000 /
#885
1$
1A
1*
b10110001 /
#890
1&
0*
b10110010 /
#895
1#
0$
10
0A
1=
1*
b10110011 /
#900
00
1B
0=
1+
0&
0*
b10110100 /
#905
1$
1A
1*
b10110101 /
#910
1&
0*
b10110110 /
#915
1"
0#
12
0$
10
14
0A
1=
1*
b10110111 /
#920
0"
1#
02
00
04
0=
1'
0+
0&
0*
b10111000 /
#925
1$
1A
1*
b10111001 /
#930
1&
0*
b10111010 /
#935
1"
0#
12
0$
10
14
0A
1=
1*
b10111011 /
#940
00
04
0B
1>
0=
1+
0&
0*
b10111100 /
#945
1$
1A
1*
b10111101 /
#950
1&
0*
b10111110 /
#955
1#
0$
10
0A
1=
1*
b10111111 /
#960
0"
0#
05
0<
02
00
0D
1@
0?
0>
0=
1-
0(
0,
0'
0+
0&
0*
b11000000 /
#965
1$
1A
1*
b11000001 /
#970
1&
0*
b11000010 /
#975
1#
0$
10
0A
1=
1*
b11000011 /
#980
00
1B
0=
1+
0&
0*
b11000100 /
#985
1$
1A
1*
b11000101 /
#990
1&
0*
b11000110 /
#995
1"
0#
12
0$
10
14
0A
1=
1*
b11000111 /
#1000
0"
1#
02
00
04
0=
1'
0+
0&
0*
b11001000 /
#1005
1$
1A
1*
b11001001 /
#1010
1&
0*
b11001010 /
#1015
1"
0#
12
0$
10
14
0A
1=
1*
b11001011 /
#1020
00
04
0B
1>
0=
1+
0&
0*
b11001100 /
#1025
1$
1A
1*
b11001101 /
#1030
1&
0*
b11001110 /
#1035
1#
0$
10
0A
1=
1*
b11001111 /
#1040
0#
02
00
1C
0>
0=
1,
0'
0+
0&
0*
b11010000 /
#1045
1$
1A
1*
b11010001 /
#1050
1&
0*
b11010010 /
#1055
1#
0$
10
0A
1=
1*
b11010011 /
#1060
00
1B
0=
1+
0&
0*
b11010100 /
#1065
1$
1A
1*
b11010101 /
#1070
1&
0*
b11010110 /
#1075
0"
1!
0#
12
15
0$
10
14
17
0A
1=
1*
b11010111 /
#1080
1"
0!
1#
02
05
00
04
07
0=
1'
0+
0&
0*
b11011000 /
#1085
1$
1A
1*
b11011001 /
#1090
1&
0*
b11011010 /
#1095
0"
1!
0#
12
15
0$
10
14
17
0A
1=
1*
b11011011 /
#1100
18
00
04
07
0B
1>
0=
1+
0&
0*
b11011100 /
#1105
1$
1A
1*
b11011101 /
#1110
1&
0*
b11011110 /
#1115
1#
0$
10
0A
1=
1*
b11011111 /
#1120
0!
1"
05
0#
02
08
00
0>
0=
1(
0,
0'
0+
0&
0*
b11100000 /
#1125
1$
1A
1*
b11100001 /
#1130
1&
0*
b11100010 /
#1135
1#
0$
10
0A
1=
1*
b11100011 /
#1140
00
1B
0=
1+
0&
0*
b11100100 /
#1145
1$
1A
1*
b11100101 /
#1150
1&
0*
b11100110 /
#1155
0"
1!
0#
12
15
0$
10
14
17
0A
1=
1*
b11100111 /
#1160
1"
0!
1#
02
05
00
04
07
0=
1'
0+
0&
0*
b11101000 /
#1165
1$
1A
1*
b11101001 /
#1170
1&
0*
b11101010 /
#1175
0"
1!
0#
12
15
0$
10
14
17
0A
1=
1*
b11101011 /
#1180
18
00
04
07
0B
1>
0=
1+
0&
0*
b11101100 /
#1185
1$
1A
1*
b11101101 /
#1190
1&
0*
b11101110 /
#1195
1#
0$
10
0A
1=
1*
b11101111 /
#1200
0#
02
08
00
0C
1?
0>
0=
1,
0'
0+
0&
0*
b11110000 /
#1205
1$
1A
1*
b11110001 /
#1210
1&
0*
b11110010 /
#1215
1#
0$
10
0A
1=
1*
b11110011 /
#1220
00
1B
0=
1+
0&
0*
b11110100 /
#1225
1$
1A
1*
b11110101 /
#1230
1&
0*
b11110110 /
#1235
1"
0#
12
0$
10
14
0A
1=
1*
b11110111 /
#1240
0"
1#
02
00
04
0=
1'
0+
0&
0*
b11111000 /
#1245
1$
1A
1*
b11111001 /
#1250
1&
0*
b11111010 /
#1255
1"
0#
12
0$
10
14
0A
1=
1*
b11111011 /
#1260
00
04
0B
1>
0=
1+
0&
0*
b11111100 /
#1265
1$
1A
1*
b11111101 /
#1270
1&
0*
b11111110 /
#1275
1#
0$
10
0A
1=
1*
b11111111 /
#1280
0%
0!
0"
0#
05
02
00
0@
0?
0>
0=
0)
0-
0(
0,
0'
0+
0&
0*
b100000000 /
#1285
b100000001 /
